setup.py
upc_item_db_api/__init__.py
upc_item_db_api/upc_item_db_api.py
upc_item_db_api.egg-info/PKG-INFO
upc_item_db_api.egg-info/SOURCES.txt
upc_item_db_api.egg-info/dependency_links.txt
upc_item_db_api.egg-info/requires.txt
upc_item_db_api.egg-info/top_level.txt