Metadata-Version: 1.0
Name: upc-item-db-api
Version: 0.1.1
Summary: Python wrapper for UPC Item DB API
Home-page: https://github.com/benmusch/upc-item-db-api-python
Author: Ben Muschol
Author-email: benmuschol@gmail.com
License: MIT
Platform: UNKNOWN
